bqapi/__init__.py
bqapi/blockable_module.py
bqapi/bqclass.py
bqapi/bqfeature.py
bqapi/casauth.py
bqapi/cmd.py
bqapi/comm.py
bqapi/exception.py
bqapi/services.py
bqapi/types.py
bqapi/util.py
bqapi/xmldict.py
bqapi/RequestsMonkeyPatch/__init__.py
bqapi/RequestsMonkeyPatch/monkeypatch.py
bqapi/RequestsMonkeyPatch/requests_patch.py
bqapi/tests/__init__.py
bqapi/tests/conftest.py
bqapi/tests/test_bqapi.py
bqapi/tests/test_bqclass.py
bqapi/tests/test_bqfeature.py
bqapi/tests/test_comm.py
bqapi/tests/test_util.py
bqapi/tests/util.py
tests/__init__.py
tests/conftest.py
tests/test_bqapi.py
tests/test_bqclass.py
tests/test_bqfeature.py
tests/test_comm.py
tests/test_util.py
tests/util.py
bisque_api-0.5.12.2.dist-info/METADATA
bisque_api-0.5.12.2.dist-info/WHEEL
bisque_api-0.5.12.2.dist-info/top_level.txt
bisque_api-0.5.12.2.dist-info/zip-safe
bisque_api-0.5.12.2.dist-info/RECORD
