Metadata-Version: 2.1
Name: bisque-api
Version: 0.5.12.2
Summary: Bisque Module API
Home-page: https://www.viqi.org
Author: ViQi Inc
Author-email: devops@viqi.org
License: UNKNOWN
Platform: UNKNOWN
Classifier: Programming Language :: Python :: 2
Classifier: Programming Language :: Python :: 2.7
Classifier: Programming Language :: Python :: 3
Classifier: Programming Language :: Python :: 3.5
Classifier: Programming Language :: Python :: 3.6
Classifier: Programming Language :: Python :: 3.7
Classifier: License :: OSI Approved :: BSD License
Classifier: Operating System :: OS Independent
Requires-Dist: requests (>=2.25)
Requires-Dist: requests-toolbelt (>=0.8)
Requires-Dist: future
Requires-Dist: configparser
Provides-Extra: cas
Requires-Dist: BeautifulSoup4 ; extra == 'cas'
Provides-Extra: feature
Requires-Dist: tables ; extra == 'feature'
Provides-Extra: image_service
Requires-Dist: tifffile ; extra == 'image_service'
Requires-Dist: tables ; extra == 'image_service'
Provides-Extra: lxml
Requires-Dist: lxml ; extra == 'lxml'
Provides-Extra: table
Requires-Dist: tables ; extra == 'table'
